bertzoo/SimBert.py
bertzoo/__init__.py
bertzoo/cpm_lm.py
bertzoo/simbert2vec.py
bertzoo/simbert_v2.py
bertzoo/t5_fintune.py
bertzoo/data/__init__.py
bertzoo/utils/GPT2.py
bertzoo/utils/__init__.py
bertzoo/utils/bert4keras_utils.py
BertZoo-2021.9.7.9.57.29.dist-info/LICENSE
BertZoo-2021.9.7.9.57.29.dist-info/METADATA
BertZoo-2021.9.7.9.57.29.dist-info/WHEEL
BertZoo-2021.9.7.9.57.29.dist-info/entry_points.txt
BertZoo-2021.9.7.9.57.29.dist-info/top_level.txt
BertZoo-2021.9.7.9.57.29.dist-info/RECORD
