Metadata-Version: 2.1
Name: BertZoo
Version: 2021.9.7.9.57.29
Summary: description
Home-page: https://github.com/Jie-Yuan/BertZoo
Author: YuanJie
Author-email: 313303303@qq.com
Maintainer: JieYuan
Maintainer-email: 313303303@qq.com
License: Apache
Keywords: tool wheel,yuanjie,utils
Platform: all
Classifier: Operating System :: OS Independent
Classifier: Intended Audience :: Developers
Classifier: License :: OSI Approved :: MIT License
Classifier: Programming Language :: Python
Classifier: Programming Language :: Python :: Implementation
License-File: LICENSE
Requires-Dist: meutils
Requires-Dist: jieba
Requires-Dist: bert4keras
